tmuxipy
