Metadata-Version: 1.1
Name: tmuxipy
Version: 0.1.10
Summary: Manage Tmux sessions legitly
Home-page: https://github.com/milin/tmuxipy
Author: Milind Shakya
Author-email: sh.milind@gmail.com
License: BSD
Keywords: tmux
Platform: UNKNOWN
Classifier: Development Status :: 2 - Pre-Alpha
Classifier: Intended Audience :: Developers
Classifier: License :: OSI Approved :: BSD License
Classifier: Natural Language :: English
Classifier: Programming Language :: Python :: 2
Classifier: Programming Language :: Python :: 2.6
Classifier: Programming Language :: Python :: 2.7
